hawk_sdk/__init__.py
hawk_sdk/api/__init__.py
hawk_sdk/api/equities/__init__.py
hawk_sdk/api/equities/main.py
hawk_sdk/api/equities/repository.py
hawk_sdk/api/equities/service.py
hawk_sdk/api/futures/__init__.py
hawk_sdk/api/futures/main.py
hawk_sdk/api/futures/repository.py
hawk_sdk/api/futures/service.py
hawk_sdk/api/ice_bofa_bonds_indices/__init__.py
hawk_sdk/api/ice_bofa_bonds_indices/main.py
hawk_sdk/api/ice_bofa_bonds_indices/repository.py
hawk_sdk/api/ice_bofa_bonds_indices/service.py
hawk_sdk/api/system/__init__.py
hawk_sdk/api/system/main.py
hawk_sdk/api/system/repository.py
hawk_sdk/api/system/service.py
hawk_sdk/api/universal/__init__.py
hawk_sdk/api/universal/main.py
hawk_sdk/api/universal/repository.py
hawk_sdk/api/universal/service.py
hawk_sdk/core/__init__.py
hawk_sdk/core/common/__init__.py
hawk_sdk/core/common/base_enum.py
hawk_sdk/core/common/constants.py
hawk_sdk/core/common/data_object.py
hawk_sdk/core/common/utils.py
hawk_sdk-0.0.19.dist-info/METADATA
hawk_sdk-0.0.19.dist-info/WHEEL
hawk_sdk-0.0.19.dist-info/top_level.txt
hawk_sdk-0.0.19.dist-info/RECORD
