Metadata-Version: 2.4
Name: hawk-sdk
Version: 0.0.19
Requires-Dist: google-cloud-bigquery
Requires-Dist: pandas
Dynamic: requires-dist
